django_cyverse_auth/__init__.py
django_cyverse_auth/admin.py
django_cyverse_auth/authBackends.py
django_cyverse_auth/decorators.py
django_cyverse_auth/exceptions.py
django_cyverse_auth/models.py
django_cyverse_auth/session.py
django_cyverse_auth/settings.py
django_cyverse_auth/token.py
django_cyverse_auth/urls.py
django_cyverse_auth/views.py
django_cyverse_auth/migrations/0001_initial.py
django_cyverse_auth/migrations/0002_resize_charfield_mysql_limits.py
django_cyverse_auth/migrations/__init__.py
django_cyverse_auth/protocol/__init__.py
django_cyverse_auth/protocol/cas.py
django_cyverse_auth/protocol/globus.py
django_cyverse_auth/protocol/jwt_oauth.py
django_cyverse_auth/protocol/ldap.py
django_cyverse_auth/protocol/oauth.py
django_cyverse_auth/protocol/wso2.py
django_cyverse_auth-1.2.0.dist-info/LICENSE
django_cyverse_auth-1.2.0.dist-info/METADATA
django_cyverse_auth-1.2.0.dist-info/WHEEL
django_cyverse_auth-1.2.0.dist-info/top_level.txt
django_cyverse_auth-1.2.0.dist-info/RECORD
