Metadata-Version: 2.1
Name: django-cyverse-auth
Version: 1.2.0
Summary: Authentication support for CyVerse Django applications.
Home-page: https://github.com/CyVerse/django-cyverse-auth
Author: CyVerse
Author-email: atmodevs@gmail.com
License: BSD License, 3 clause
Platform: UNKNOWN
Classifier: Development Status :: 4 - Beta
Classifier: Environment :: Web Environment
Classifier: Framework :: Django
Classifier: Framework :: Django :: 1.7
Classifier: Framework :: Django :: 1.8
Classifier: Framework :: Django :: 1.9
Classifier: Intended Audience :: Developers
Classifier: Intended Audience :: Information Technology
Classifier: License :: OSI Approved :: BSD License
Classifier: Natural Language :: English
Classifier: Operating System :: OS Independent
Classifier: Programming Language :: Python
Classifier: Topic :: Software Development :: Libraries
Classifier: Topic :: System :: Systems Administration
Classifier: Topic :: System :: Systems Administration :: Authentication/Directory
Requires-Dist: caslib.py (>=2.3.0)
Requires-Dist: apache-libcloud
Requires-Dist: oauth2client
Requires-Dist: djangorestframework
Requires-Dist: jwt.py
Requires-Dist: python-ldap
Requires-Dist: requests[security]
Requires-Dist: threepio
Requires-Dist: python-keystoneclient
Requires-Dist: keystoneauth1
